.gitignore
CHANGES.rst
MANIFEST.in
README.rst
setup.cfg
setup.py
docs/.gitignore
docs/Makefile
docs/api.rst
docs/conf.py
docs/glossary.rst
docs/index.rst
khufu_deform/__init__.py
khufu_deform/_api.py
khufu_deform/demo.py
khufu_deform/tests.py
khufu_deform/utils.py
khufu_deform/views.py
khufu_deform.egg-info/PKG-INFO
khufu_deform.egg-info/SOURCES.txt
khufu_deform.egg-info/dependency_links.txt
khufu_deform.egg-info/entry_points.txt
khufu_deform.egg-info/not-zip-safe
khufu_deform.egg-info/requires.txt
khufu_deform.egg-info/top_level.txt
khufu_deform/static/style.css
khufu_deform/templates/deform-head.jinja2
khufu_deform/templates/generic-form.jinja2
khufu_deform/templates/generic-view.jinja2
khufu_deform/templates/layout.jinja2
khufu_deform/templates/listing.jinja2