Metadata-Version: 1.0
Name: khufu-deform
Version: 1.0a1
Summary: Deform bindings and automatic CRUD views for SQLAlchemy models on Pyramid
Home-page: http://khufuproject.github.com/khufu_deform
Author: Rocky Burt
Author-email: rocky@serverzen.com
License: BSD
Keywords: pyramid khufu deform
Platform: UNKNOWN
Classifier: License :: OSI Approved :: BSD License
Classifier: Programming Language :: Python
Classifier: Topic :: Internet :: WWW/HTTP :: WSGI
